Metadata-Version: 2.1
Name: tableintuit
Version: 0.1.8
Summary: Guess the structure and datatypes of row data, such as from a spreadsheet
Home-page: https://github.com/Metatab/tableintuit.git
Author: eric@civicknowledge.com
Author-email: eric@civicknowledge.com
License: MIT
Classifier: Development Status :: 4 - Beta
Classifier: Intended Audience :: Developers
Classifier: License :: OSI Approved :: MIT License
Classifier: Operating System :: OS Independent
Classifier: Programming Language :: Python
Classifier: Programming Language :: Python :: 3.4
Classifier: Topic :: Software Development :: Libraries :: Python Modules
License-File: LICENSE
